<?xml version="1.0"?>
<!DOCTYPE hibernate-mapping PUBLIC "-//Hibernate/Hibernate Mapping DTD 3.0//EN"
"http://hibernate.sourceforge.net/hibernate-mapping-3.0.dtd">
<!-- Generated 2014-4-23 17:05:01 by Hibernate Tools 3.4.0.CR1 -->
<hibernate-mapping>
    <class name="com.sizheng.afl.pojo.entity.MenuCategory" table="menu_category" catalog="afl">
        <id name="id" type="java.lang.Long">
            <column name="id" />
            <generator class="identity" />
        </id>
        <property name="name" type="string">
            <column name="name" />
        </property>
        <property name="owner" type="string">
            <column name="owner" />
        </property>
        <property name="isDelete" type="java.lang.Short">
            <column name="is_delete" />
        </property>
        <property name="dateTime" type="timestamp">
            <column name="date_time" length="19" />
        </property>
    </class>
</hibernate-mapping>
